lihim/__init__.py
lihim/config.py
lihim/controller.py
lihim/main.py
lihim/models.py
lihim-1.1.0.dist-info/entry_points.txt
lihim-1.1.0.dist-info/LICENSE
lihim-1.1.0.dist-info/WHEEL
lihim-1.1.0.dist-info/METADATA
lihim-1.1.0.dist-info/RECORD
