Metadata-Version: 2.1
Name: lihim
Version: 1.1.0
Summary: CLI for managing secret keys, tokens, sensitive and/or public key-value pairs.
License: MIT
Author: Neil Van
Author-email: nvq.alino@gmail.com
Requires-Python: >=3.8,<4.0
Classifier: License :: OSI Approved :: MIT License
Classifier: Programming Language :: Python :: 3
Classifier: Programming Language :: Python :: 3.8
Classifier: Programming Language :: Python :: 3.9
Requires-Dist: PyNaCl (>=1.4.0,<2.0.0)
Requires-Dist: peewee (>=3.14.4,<4.0.0)
Requires-Dist: typer (>=0.3.2,<0.4.0)
